setup.py
udacity_probability/Binomialdistribution.py
udacity_probability/Gaussiandistribution.py
udacity_probability/Generaldistribution.py
udacity_probability/__init__.py
udacity_probability.egg-info/PKG-INFO
udacity_probability.egg-info/SOURCES.txt
udacity_probability.egg-info/dependency_links.txt
udacity_probability.egg-info/not-zip-safe
udacity_probability.egg-info/top_level.txt