Metadata-Version: 1.0
Name: udacity-probability
Version: 0.1
Summary: Gaussian distributions
Home-page: UNKNOWN
Author: Najla Alharbi
Author-email: najlachai@gmail.com
License: UNKNOWN
Platform: UNKNOWN
